AUTHORS
CHANGELOG.txt
DESCRIPTION
LICENSE
MANIFEST.in
README.rst
requirements.txt
runtests.py
setup.cfg
setup.py
test_requirements.txt
tox.ini
eim_comments/__init__.py
eim_comments/admin.py
eim_comments/models.py
eim_comments/urls.py
eim_comments/views.py
eim_comments.egg-info/PKG-INFO
eim_comments.egg-info/SOURCES.txt
eim_comments.egg-info/dependency_links.txt
eim_comments.egg-info/requires.txt
eim_comments.egg-info/top_level.txt
eim_comments/management/__init__.py
eim_comments/management/commands/__init__.py
eim_comments/management/commands/hello.py
eim_comments/static/.empty
eim_comments/static/eim_comments/.empty
eim_comments/templates/eim_comments/.empty
eim_comments/templatetags/__init__.py
eim_comments/templatetags/eim_comments_tags.py
eim_comments/tests/__init__.py
eim_comments/tests/models_tests.py
eim_comments/tests/settings.py
eim_comments/tests/test_settings.py
eim_comments/tests/urls.py
eim_comments/tests/test_app/__init__.py
eim_comments/tests/test_app/models.py
eim_comments/tests/test_app/templates/400.html
eim_comments/tests/test_app/templates/500.html