Metadata-Version: 1.0
Name: eim-comments
Version: 0.1
Summary: Reusable comments app for learning purposes.
